pysyslog/__init__.py
pysyslog/cli.py
pysyslog/pysyslog.py
pysyslog-0.1.0.dist-info/METADATA
pysyslog-0.1.0.dist-info/RECORD
pysyslog-0.1.0.dist-info/WHEEL
pysyslog-0.1.0.dist-info/entry_points.txt
pysyslog-0.1.0.dist-info/top_level.txt
