Metadata-Version: 2.1
Name: pysyslog
Version: 0.1.0
Summary: Fast, efficient and useful syslog collector using TCP and optional TLS
Home-page: https://github.com/ilovetux/pysyslog
Author: Clifford Bressette
Author-email: cliffbressette@gmail.com
License: GNU General Public License v3
Keywords: pysyslog
Platform: UNKNOWN
Classifier: Development Status :: 2 - Pre-Alpha
Classifier: Intended Audience :: Developers
Classifier: License :: OSI Approved :: GNU General Public License v3 (GPLv3)
Classifier: Natural Language :: English
Classifier: Programming Language :: Python :: 2
Classifier: Programming Language :: Python :: 2.7
Classifier: Programming Language :: Python :: 3
Classifier: Programming Language :: Python :: 3.4
Classifier: Programming Language :: Python :: 3.5
Classifier: Programming Language :: Python :: 3.6
Classifier: Programming Language :: Python :: 3.7
Requires-Dist: Click (>=6.0)
